content/code/verilog_note_about_delay/adder_t1.v
`timescale 1ns / 100ps


module adder_t1 (co, sum, a, b, ci);
  output co;
  output [3:0] sum;
  input [3:0] a, b;
  input ci;
  reg co;
  reg [3:0] sum;
  always @(a or b or ci)
    #12 {co, sum} = a + b + ci;
endmodule

code/verilog_note_about_delay/tb_adder_t1.v
`timescale 1ns / 100ps

module tb_adder_t1;

reg [3:0] a;
reg [3:0] b;
reg ci;
wire [3:0] sum;
wire co;

adder_t1 u_adder_t1 (
    .co(co), 
    .sum(sum), 
    .a(a), 
    .b(b), 
    .ci(ci)
    );

initial begin
    #0 a = 4'h0;
    b = 4'h0;
    ci = 1'b0;
    #15 a = 4'hA;
    #2  b = 4'h3;
    #2  a = 4'h2;
    #2  a = 4'hF;
    #3  ci = 4'h1;

end


initial begin
  $dumpfile("tb_adder_t1.vcd");
  $dumpvars(0,tb_adder_t1); 
  #36 $finish;
end

endmodule

code/verilog_note_about_delay/tb_adder_t1.vcd
$date
	Fri Jul 30 18:06:54 2021
$end
$version
	Icarus Verilog
$end
$timescale
	100ps
$end
$scope module tb_adder_t1 $end
$var wire 4 ! sum [3:0] $end
$var wire 1 " co $end
$var reg 4 # a [3:0] $end
$var reg 4 $ b [3:0] $end
$var reg 1 % ci $end
$scope module u_adder_t1 $end
$var wire 4 & a [3:0] $end
$var wire 4 ' b [3:0] $end
$var wire 1 % ci $end
$var reg 1 " co $end
$var reg 4 ( sum [3:0] $end
$upscope $end
$upscope $end
$enddefinitions $end
#0
$dumpvars
bx (
b0 '
b0 &
0%
b0 $
b0 #
x"
bx !
$end
#120
0"
b0 !
b0 (
#150
b1010 #
b1010 &
#170
b11 $
b11 '
#190
b10 #
b10 &
#210
b1111 #
b1111 &
#240
1%
#270
1"
b11 !
b11 (
